harcx-0.2.0.dist-info/licenses/LICENSE
reference_checker/__init__.py
reference_checker/books.py
reference_checker/cli.py
reference_checker/dblp.py
reference_checker/google_scholar.py
reference_checker/matcher.py
reference_checker/models.py
reference_checker/parser.py
reference_checker/scholar.py
reference_checker/web_checker.py
harcx-0.2.0.dist-info/METADATA
harcx-0.2.0.dist-info/WHEEL
harcx-0.2.0.dist-info/entry_points.txt
harcx-0.2.0.dist-info/top_level.txt
harcx-0.2.0.dist-info/RECORD
