Metadata-Version: 2.4
Name: harcx
Version: 0.2.0
Summary: Verify .bib file citations against academic databases (Semantic Scholar, DBLP, Google Scholar, Open Library)
License: MIT
Keywords: bibtex,bibliography,semantic-scholar,dblp,citations,reference-checker,latex
Classifier: Development Status :: 3 - Alpha
Classifier: Intended Audience :: Science/Research
Classifier: License :: OSI Approved :: MIT License
Classifier: Programming Language :: Python :: 3
Classifier: Programming Language :: Python :: 3.10
Classifier: Programming Language :: Python :: 3.11
Classifier: Programming Language :: Python :: 3.12
Requires-Python: >=3.10
License-File: LICENSE
Requires-Dist: bibtexparser<2.0,>=1.4
Requires-Dist: httpx>=0.24.0
Requires-Dist: rapidfuzz>=3.0.0
Requires-Dist: beautifulsoup4>=4.12.0
Requires-Dist: scholarly>=1.7.0
Provides-Extra: dev
Requires-Dist: pytest>=7.0; extra == "dev"
Requires-Dist: pytest-cov>=4.0; extra == "dev"
Dynamic: license-file
